dynamic_overload/__init__.py
dynamic_overload/overload.py
dynamic_overload/py.typed
dynamic_overload-0.2.0.dist-info/LICENSE
dynamic_overload-0.2.0.dist-info/METADATA
dynamic_overload-0.2.0.dist-info/WHEEL
dynamic_overload-0.2.0.dist-info/top_level.txt
dynamic_overload-0.2.0.dist-info/RECORD
