Metadata-Version: 2.1
Name: dynamic-overload
Version: 0.2.0
Summary: A basic package that allows to overload functions and class functions dynamically depending on the input types.
Home-page: https://github.com/ferranSanchezLlado/dynamic_overload.git
Author: Ferran Sanchez Llado
Author-email: ferransll@gmail.com
License: MIT
Platform: any
Classifier: Programming Language :: Python :: 3
Classifier: Programming Language :: Python :: 3 :: Only
Classifier: License :: OSI Approved :: MIT License
Classifier: Operating System :: OS Independent
Classifier: Development Status :: 3 - Alpha
Classifier: Intended Audience :: Developers
Classifier: Intended Audience :: Science/Research
Classifier: Topic :: Scientific/Engineering
Classifier: Topic :: Software Development
Classifier: Topic :: Software Development :: Libraries
Classifier: Topic :: Software Development :: Libraries :: Python Modules
Classifier: Typing :: Typed
Requires-Python: >=3.10
License-File: LICENSE
Provides-Extra: testing
Requires-Dist: pytest (>=6.0) ; extra == 'testing'
Requires-Dist: pytest-cov (>=2.10) ; extra == 'testing'
Requires-Dist: flake8 (>=3.9) ; extra == 'testing'
Requires-Dist: pylint (>=2.8) ; extra == 'testing'
Requires-Dist: mypy (>=0.812) ; extra == 'testing'
